anypy/__init__.py
anypy/_version.py
anypy/benchmark/__init__.py
anypy/benchmark/chrono.py
anypy/data/metadata_dataset_dict.py
anypy/latex/__init__.py
anypy/latex/dataframe.py
anypy/nn/blocks.py
anypy/nn/dyncnn.py
anypy/nn/utils.py
anypy-0.1.1.dist-info/LICENSE
anypy-0.1.1.dist-info/METADATA
anypy-0.1.1.dist-info/WHEEL
anypy-0.1.1.dist-info/top_level.txt
anypy-0.1.1.dist-info/RECORD
