Metadata-Version: 2.1
Name: anypy
Version: 0.1.1
Summary: A collection of python utilities, without hard dependencies
Home-page: https://github.com/lucmos/anypy
Author: Luca Moschella
Author-email: luca.moschella94@gmail.com
License: MIT Licence
Keywords: python
Platform: UNKNOWN
License-File: LICENSE
Provides-Extra: core
Requires-Dist: pandas ; extra == 'core'
Requires-Dist: hydra-core ; extra == 'core'
Requires-Dist: datasets ; extra == 'core'
Requires-Dist: lightning ; extra == 'core'
Provides-Extra: dev
Requires-Dist: black ; extra == 'dev'
Requires-Dist: flake8 ; extra == 'dev'
Requires-Dist: isort ; extra == 'dev'
Requires-Dist: pre-commit ; extra == 'dev'
Requires-Dist: bandit ; extra == 'dev'
Requires-Dist: pandas ; extra == 'dev'
Requires-Dist: hydra-core ; extra == 'dev'
Requires-Dist: datasets ; extra == 'dev'
Requires-Dist: lightning ; extra == 'dev'
Requires-Dist: pytest ; extra == 'dev'
Requires-Dist: pytest-cov ; extra == 'dev'
Requires-Dist: mkdocs ; extra == 'dev'
Requires-Dist: mkdocs-material ; extra == 'dev'
Requires-Dist: mike ; extra == 'dev'
Provides-Extra: docs
Requires-Dist: mkdocs ; extra == 'docs'
Requires-Dist: mkdocs-material ; extra == 'docs'
Requires-Dist: mike ; extra == 'docs'
Provides-Extra: test
Requires-Dist: pytest ; extra == 'test'
Requires-Dist: pytest-cov ; extra == 'test'
